<?xml version="1.0" encoding="UTF-8"?>
<!DOCTYPE mapper PUBLIC "-//mybatis.org//DTD Mapper 3.0//EN" "http://mybatis.org/dtd/mybatis-3-mapper.dtd">
<mapper namespace="com.fairyland.xrobot.modular.xrobot.dao.mapper.AppVersionMapper">
  <resultMap id="BaseResultMap" type="com.fairyland.xrobot.modular.xrobot.domain.AppVersion">
    <!--
      WARNING - @mbggenerated
      This element is automatically generated by MyBatis Generator, do not modify.
    -->
    <id column="id" jdbcType="BIGINT" property="id" />
    <result column="osname" jdbcType="VARCHAR" property="osname" />
    <result column="context" jdbcType="VARCHAR" property="context" />
    <result column="title" jdbcType="VARCHAR" property="title" />
    <result column="forceFlag" jdbcType="CHAR" property="forceflag" />
    <result column="appversion" jdbcType="VARCHAR" property="appversion" />
    <result column="downloadurl" jdbcType="VARCHAR" property="downloadurl" />
    <result column="create_by" jdbcType="VARCHAR" property="createBy" />
    <result column="create_date" jdbcType="TIMESTAMP" property="createDate" />
    <result column="update_by" jdbcType="VARCHAR" property="updateBy" />
    <result column="update_date" jdbcType="TIMESTAMP" property="updateDate" />
    <result column="remarks" jdbcType="VARCHAR" property="remarks" />
    <result column="del_flag" jdbcType="CHAR" property="delFlag" />
  </resultMap>
  <sql id="Example_Where_Clause">
    <!--
      WARNING - @mbggenerated
      This element is automatically generated by MyBatis Generator, do not modify.
    -->
    <where>
      <foreach collection="oredCriteria" item="criteria" separator="or">
        <if test="criteria.valid">
          <trim prefix="(" prefixOverrides="and" suffix=")">
            <foreach collection="criteria.criteria" item="criterion">
              <choose>
                <when test="criterion.noValue">
                  and ${criterion.condition}
                </when>
                <when test="criterion.singleValue">
                  and ${criterion.condition} #{criterion.value}
                </when>
                <when test="criterion.betweenValue">
                  and ${criterion.condition} #{criterion.value} and #{criterion.secondValue}
                </when>
                <when test="criterion.listValue">
                  and ${criterion.condition}
                  <foreach close=")" collection="criterion.value" item="listItem" open="(" separator=",">
                    #{listItem}
                  </foreach>
                </when>
              </choose>
            </foreach>
          </trim>
        </if>
      </foreach>
    </where>
  </sql>
  <sql id="Update_By_Example_Where_Clause">
    <!--
      WARNING - @mbggenerated
      This element is automatically generated by MyBatis Generator, do not modify.
    -->
    <where>
      <foreach collection="example.oredCriteria" item="criteria" separator="or">
        <if test="criteria.valid">
          <trim prefix="(" prefixOverrides="and" suffix=")">
            <foreach collection="criteria.criteria" item="criterion">
              <choose>
                <when test="criterion.noValue">
                  and ${criterion.condition}
                </when>
                <when test="criterion.singleValue">
                  and ${criterion.condition} #{criterion.value}
                </when>
                <when test="criterion.betweenValue">
                  and ${criterion.condition} #{criterion.value} and #{criterion.secondValue}
                </when>
                <when test="criterion.listValue">
                  and ${criterion.condition}
                  <foreach close=")" collection="criterion.value" item="listItem" open="(" separator=",">
                    #{listItem}
                  </foreach>
                </when>
              </choose>
            </foreach>
          </trim>
        </if>
      </foreach>
    </where>
  </sql>
  <sql id="Base_Column_List">
    <!--
      WARNING - @mbggenerated
      This element is automatically generated by MyBatis Generator, do not modify.
    -->
    id, osname, context, title, forceFlag, appversion, downloadurl, create_by, create_date, 
    update_by, update_date, remarks, del_flag
  </sql>
  <select id="selectByExample" parameterType="com.fairyland.xrobot.modular.xrobot.domain.AppVersionExample" resultMap="BaseResultMap">
    <!--
      WARNING - @mbggenerated
      This element is automatically generated by MyBatis Generator, do not modify.
    -->
    select
    <if test="distinct">
      distinct
    </if>
    <include refid="Base_Column_List" />
    from app_version
    <if test="_parameter != null">
      <include refid="Example_Where_Clause" />
    </if>
    <if test="orderByClause != null">
      order by ${orderByClause}
    </if>
  </select>
  <select id="selectByPrimaryKey" parameterType="java.lang.Long" resultMap="BaseResultMap">
    <!--
      WARNING - @mbggenerated
      This element is automatically generated by MyBatis Generator, do not modify.
    -->
    select 
    <include refid="Base_Column_List" />
    from app_version
    where id = #{id,jdbcType=BIGINT}
  </select>
  <delete id="deleteByPrimaryKey" parameterType="java.lang.Long">
    <!--
      WARNING - @mbggenerated
      This element is automatically generated by MyBatis Generator, do not modify.
    -->
    delete from app_version
    where id = #{id,jdbcType=BIGINT}
  </delete>
  <delete id="deleteByExample" parameterType="com.fairyland.xrobot.modular.xrobot.domain.AppVersionExample">
    <!--
      WARNING - @mbggenerated
      This element is automatically generated by MyBatis Generator, do not modify.
    -->
    delete from app_version
    <if test="_parameter != null">
      <include refid="Example_Where_Clause" />
    </if>
  </delete>
  <insert id="insert" parameterType="com.fairyland.xrobot.modular.xrobot.domain.AppVersion">
    <!--
      WARNING - @mbggenerated
      This element is automatically generated by MyBatis Generator, do not modify.
    -->
    insert into app_version (id, osname, context, 
      title, forceFlag, appversion, 
      downloadurl, create_by, create_date, 
      update_by, update_date, remarks, 
      del_flag)
    values (#{id,jdbcType=BIGINT}, #{osname,jdbcType=VARCHAR}, #{context,jdbcType=VARCHAR}, 
      #{title,jdbcType=VARCHAR}, #{forceflag,jdbcType=CHAR}, #{appversion,jdbcType=VARCHAR}, 
      #{downloadurl,jdbcType=VARCHAR}, #{createBy,jdbcType=VARCHAR}, #{createDate,jdbcType=TIMESTAMP}, 
      #{updateBy,jdbcType=VARCHAR}, #{updateDate,jdbcType=TIMESTAMP}, #{remarks,jdbcType=VARCHAR}, 
      #{delFlag,jdbcType=CHAR})
  </insert>
  <insert id="insertSelective" parameterType="com.fairyland.xrobot.modular.xrobot.domain.AppVersion">
    <!--
      WARNING - @mbggenerated
      This element is automatically generated by MyBatis Generator, do not modify.
    -->
    insert into app_version
    <trim prefix="(" suffix=")" suffixOverrides=",">
      <if test="id != null">
        id,
      </if>
      <if test="osname != null">
        osname,
      </if>
      <if test="context != null">
        context,
      </if>
      <if test="title != null">
        title,
      </if>
      <if test="forceflag != null">
        forceFlag,
      </if>
      <if test="appversion != null">
        appversion,
      </if>
      <if test="downloadurl != null">
        downloadurl,
      </if>
      <if test="createBy != null">
        create_by,
      </if>
      <if test="createDate != null">
        create_date,
      </if>
      <if test="updateBy != null">
        update_by,
      </if>
      <if test="updateDate != null">
        update_date,
      </if>
      <if test="remarks != null">
        remarks,
      </if>
      <if test="delFlag != null">
        del_flag,
      </if>
    </trim>
    <trim prefix="values (" suffix=")" suffixOverrides=",">
      <if test="id != null">
        #{id,jdbcType=BIGINT},
      </if>
      <if test="osname != null">
        #{osname,jdbcType=VARCHAR},
      </if>
      <if test="context != null">
        #{context,jdbcType=VARCHAR},
      </if>
      <if test="title != null">
        #{title,jdbcType=VARCHAR},
      </if>
      <if test="forceflag != null">
        #{forceflag,jdbcType=CHAR},
      </if>
      <if test="appversion != null">
        #{appversion,jdbcType=VARCHAR},
      </if>
      <if test="downloadurl != null">
        #{downloadurl,jdbcType=VARCHAR},
      </if>
      <if test="createBy != null">
        #{createBy,jdbcType=VARCHAR},
      </if>
      <if test="createDate != null">
        #{createDate,jdbcType=TIMESTAMP},
      </if>
      <if test="updateBy != null">
        #{updateBy,jdbcType=VARCHAR},
      </if>
      <if test="updateDate != null">
        #{updateDate,jdbcType=TIMESTAMP},
      </if>
      <if test="remarks != null">
        #{remarks,jdbcType=VARCHAR},
      </if>
      <if test="delFlag != null">
        #{delFlag,jdbcType=CHAR},
      </if>
    </trim>
  </insert>
  <select id="countByExample" parameterType="com.fairyland.xrobot.modular.xrobot.domain.AppVersionExample" resultType="java.lang.Integer">
    <!--
      WARNING - @mbggenerated
      This element is automatically generated by MyBatis Generator, do not modify.
    -->
    select count(*) from app_version
    <if test="_parameter != null">
      <include refid="Example_Where_Clause" />
    </if>
  </select>
  <update id="updateByExampleSelective" parameterType="map">
    <!--
      WARNING - @mbggenerated
      This element is automatically generated by MyBatis Generator, do not modify.
    -->
    update app_version
    <set>
      <if test="record.id != null">
        id = #{record.id,jdbcType=BIGINT},
      </if>
      <if test="record.osname != null">
        osname = #{record.osname,jdbcType=VARCHAR},
      </if>
      <if test="record.context != null">
        context = #{record.context,jdbcType=VARCHAR},
      </if>
      <if test="record.title != null">
        title = #{record.title,jdbcType=VARCHAR},
      </if>
      <if test="record.forceflag != null">
        forceFlag = #{record.forceflag,jdbcType=CHAR},
      </if>
      <if test="record.appversion != null">
        appversion = #{record.appversion,jdbcType=VARCHAR},
      </if>
      <if test="record.downloadurl != null">
        downloadurl = #{record.downloadurl,jdbcType=VARCHAR},
      </if>
      <if test="record.createBy != null">
        create_by = #{record.createBy,jdbcType=VARCHAR},
      </if>
      <if test="record.createDate != null">
        create_date = #{record.createDate,jdbcType=TIMESTAMP},
      </if>
      <if test="record.updateBy != null">
        update_by = #{record.updateBy,jdbcType=VARCHAR},
      </if>
      <if test="record.updateDate != null">
        update_date = #{record.updateDate,jdbcType=TIMESTAMP},
      </if>
      <if test="record.remarks != null">
        remarks = #{record.remarks,jdbcType=VARCHAR},
      </if>
      <if test="record.delFlag != null">
        del_flag = #{record.delFlag,jdbcType=CHAR},
      </if>
    </set>
    <if test="_parameter != null">
      <include refid="Update_By_Example_Where_Clause" />
    </if>
  </update>
  <update id="updateByExample" parameterType="map">
    <!--
      WARNING - @mbggenerated
      This element is automatically generated by MyBatis Generator, do not modify.
    -->
    update app_version
    set id = #{record.id,jdbcType=BIGINT},
      osname = #{record.osname,jdbcType=VARCHAR},
      context = #{record.context,jdbcType=VARCHAR},
      title = #{record.title,jdbcType=VARCHAR},
      forceFlag = #{record.forceflag,jdbcType=CHAR},
      appversion = #{record.appversion,jdbcType=VARCHAR},
      downloadurl = #{record.downloadurl,jdbcType=VARCHAR},
      create_by = #{record.createBy,jdbcType=VARCHAR},
      create_date = #{record.createDate,jdbcType=TIMESTAMP},
      update_by = #{record.updateBy,jdbcType=VARCHAR},
      update_date = #{record.updateDate,jdbcType=TIMESTAMP},
      remarks = #{record.remarks,jdbcType=VARCHAR},
      del_flag = #{record.delFlag,jdbcType=CHAR}
    <if test="_parameter != null">
      <include refid="Update_By_Example_Where_Clause" />
    </if>
  </update>
  <update id="updateByPrimaryKeySelective" parameterType="com.fairyland.xrobot.modular.xrobot.domain.AppVersion">
    <!--
      WARNING - @mbggenerated
      This element is automatically generated by MyBatis Generator, do not modify.
    -->
    update app_version
    <set>
      <if test="osname != null">
        osname = #{osname,jdbcType=VARCHAR},
      </if>
      <if test="context != null">
        context = #{context,jdbcType=VARCHAR},
      </if>
      <if test="title != null">
        title = #{title,jdbcType=VARCHAR},
      </if>
      <if test="forceflag != null">
        forceFlag = #{forceflag,jdbcType=CHAR},
      </if>
      <if test="appversion != null">
        appversion = #{appversion,jdbcType=VARCHAR},
      </if>
      <if test="downloadurl != null">
        downloadurl = #{downloadurl,jdbcType=VARCHAR},
      </if>
      <if test="createBy != null">
        create_by = #{createBy,jdbcType=VARCHAR},
      </if>
      <if test="createDate != null">
        create_date = #{createDate,jdbcType=TIMESTAMP},
      </if>
      <if test="updateBy != null">
        update_by = #{updateBy,jdbcType=VARCHAR},
      </if>
      <if test="updateDate != null">
        update_date = #{updateDate,jdbcType=TIMESTAMP},
      </if>
      <if test="remarks != null">
        remarks = #{remarks,jdbcType=VARCHAR},
      </if>
      <if test="delFlag != null">
        del_flag = #{delFlag,jdbcType=CHAR},
      </if>
    </set>
    where id = #{id,jdbcType=BIGINT}
  </update>
  <update id="updateByPrimaryKey" parameterType="com.fairyland.xrobot.modular.xrobot.domain.AppVersion">
    <!--
      WARNING - @mbggenerated
      This element is automatically generated by MyBatis Generator, do not modify.
    -->
    update app_version
    set osname = #{osname,jdbcType=VARCHAR},
      context = #{context,jdbcType=VARCHAR},
      title = #{title,jdbcType=VARCHAR},
      forceFlag = #{forceflag,jdbcType=CHAR},
      appversion = #{appversion,jdbcType=VARCHAR},
      downloadurl = #{downloadurl,jdbcType=VARCHAR},
      create_by = #{createBy,jdbcType=VARCHAR},
      create_date = #{createDate,jdbcType=TIMESTAMP},
      update_by = #{updateBy,jdbcType=VARCHAR},
      update_date = #{updateDate,jdbcType=TIMESTAMP},
      remarks = #{remarks,jdbcType=VARCHAR},
      del_flag = #{delFlag,jdbcType=CHAR}
    where id = #{id,jdbcType=BIGINT}
  </update>
</mapper>